{"type":"FeatureCollection","crs":{"type":"name","properties":{"name":"EPSG:3005"}},"features":[{"type":"Feature","id":1,"geometry":{"type":"Polygon","coordinates":[[[1163791.4127999991,810664.22149999999],[1163791.4127999991,776069.35229999945],[1254656.1533000004,776069.35229999945],[1254656.1533000004,810664.22149999999],[1163791.4127999991,810664.22149999999]]]},"properties":{"OBJECTID":1,"FeatureID":3309,"ZOrder":null,"AnnotationClassID":0,"SymbolID":0,"Status":0,"TextString":"Cariboo ","FontName":"BC Sans","FontStyle":"Regular","FontSize":9,"Underline":0,"VerticalAlignment":2,"HorizontalAlignment":1,"XOffset":0,"YOffset":0,"Angle":0,"FontLeading":0,"WordSpacing":100,"CharacterWidth":100,"CharacterSpacing":0,"FlipAngle":90,"Override":0,"SHAPE_Length":250919.21940000355,"SHAPE_Area":3143453812.4895344}},{"type":"Feature","id":2,"geometry":{"type":"Polygon","coordinates":[[[1561265.5415000003,635359.28060000017],[1561265.5415000003,600764.41139999963],[1796598.3351000007,600764.41139999963],[1796598.3351000007,635359.28060000017],[1561265.5415000003,635359.28060000017]]]},"properties":{"OBJECTID":2,"FeatureID":3310,"ZOrder":null,"AnnotationClassID":0,"SymbolID":0,"Status":0,"TextString":"Kootenay-Boundary\n","FontName":"BC Sans","FontStyle":"Regular","FontSize":9,"Underline":0,"VerticalAlignment":2,"HorizontalAlignment":1,"XOffset":0,"YOffset":0,"Angle":0,"FontLeading":0,"WordSpacing":100,"CharacterWidth":100,"CharacterSpacing":0,"FlipAngle":90,"Override":0,"SHAPE_Length":539855.32560000196,"SHAPE_Area":8141307213.0627394}},{"type":"Feature","id":3,"geometry":{"type":"Polygon","coordinates":[[[1133944.2544,1440547.9020000007],[1133944.2544,1405953.0328000002],[1250979.9769000001,1405953.0328000002],[1250979.9769000001,1440547.9020000007],[1133944.2544,1440547.9020000007]]]},"properties":{"OBJECTID":3,"FeatureID":3311,"ZOrder":null,"AnnotationClassID":0,"SymbolID":0,"Status":0,"TextString":"Northeast ","FontName":"BC Sans","FontStyle":"Regular","FontSize":9,"Underline":0,"VerticalAlignment":2,"HorizontalAlignment":1,"XOffset":0,"YOffset":0,"Angle":0,"FontLeading":0,"WordSpacing":100,"CharacterWidth":100,"CharacterSpacing":0,"FlipAngle":90,"Override":0,"SHAPE_Length":303261.18340000138,"SHAPE_Area":4048835511.6150651}},{"type":"Feature","id":4,"geometry":{"type":"Polygon","coordinates":[[[1073006.1385999992,1155880.2166000009],[1073006.1385999992,1121285.3474000003],[1176029.0864000004,1121285.3474000003],[1176029.0864000004,1155880.2166000009],[1073006.1385999992,1155880.2166000009]]]},"properties":{"OBJECTID":4,"FeatureID":3312,"ZOrder":null,"AnnotationClassID":0,"SymbolID":0,"Status":0,"TextString":"Omineca\n","FontName":"BC Sans","FontStyle":"Regular","FontSize":9,"Underline":0,"VerticalAlignment":2,"HorizontalAlignment":1,"XOffset":0,"YOffset":0,"Angle":0,"FontLeading":0,"WordSpacing":100,"CharacterWidth":100,"CharacterSpacing":0,"FlipAngle":90,"Override":0,"SHAPE_Length":275235.63400000334,"SHAPE_Area":3564065403.7395225}},{"type":"Feature","id":5,"geometry":{"type":"Polygon","coordinates":[[[700983.01369999908,1326377.5856999997],[700983.01369999908,1291782.7164999992],[783845.58070000075,1291782.7164999992],[783845.58070000075,1326377.5856999997],[700983.01369999908,1326377.5856999997]]]},"properties":{"OBJECTID":5,"FeatureID":3313,"ZOrder":null,"AnnotationClassID":0,"SymbolID":0,"Status":0,"TextString":"Skeena ","FontName":"BC Sans","FontStyle":"Regular","FontSize":9,"Underline":0,"VerticalAlignment":2,"HorizontalAlignment":1,"XOffset":0,"YOffset":0,"Angle":0,"FontLeading":0,"WordSpacing":100,"CharacterWidth":100,"CharacterSpacing":0,"FlipAngle":90,"Override":0,"SHAPE_Length":234914.87240000442,"SHAPE_Area":2866619666.941339}},{"type":"Feature","id":6,"geometry":{"type":"Polygon","coordinates":[[[1152340.0391000006,584396.99599999934],[1152340.0391000006,515207.25760000013],[1219061.9845000003,515207.25760000013],[1219061.9845000003,584396.99599999934],[1152340.0391000006,584396.99599999934]]]},"properties":{"OBJECTID":6,"FeatureID":3314,"ZOrder":null,"AnnotationClassID":0,"SymbolID":0,"Status":0,"TextString":"South\nCoast","FontName":"BC Sans","FontStyle":"Regular","FontSize":9,"Underline":0,"VerticalAlignment":2,"HorizontalAlignment":1,"XOffset":0,"YOffset":0,"Angle":0,"FontLeading":0,"WordSpacing":100,"CharacterWidth":100,"CharacterSpacing":0,"FlipAngle":90,"Override":0,"SHAPE_Length":271823.36759999767,"SHAPE_Area":4616473947.7650051}},{"type":"Feature","id":7,"geometry":{"type":"Polygon","coordinates":[[[1279489.1391000003,645541.95959999971],[1279489.1391000003,610947.09039999917],[1536470.2118999995,610947.09039999917],[1536470.2118999995,645541.95959999971],[1279489.1391000003,645541.95959999971]]]},"properties":{"OBJECTID":7,"FeatureID":3315,"ZOrder":null,"AnnotationClassID":0,"SymbolID":0,"Status":0,"TextString":"Thompson-Okanagan","FontName":"BC Sans","FontStyle":"Regular","FontSize":9,"Underline":0,"VerticalAlignment":2,"HorizontalAlignment":1,"XOffset":0,"YOffset":0,"Angle":0,"FontLeading":0,"WordSpacing":100,"CharacterWidth":100,"CharacterSpacing":0,"FlipAngle":90,"Override":0,"SHAPE_Length":583151.88399999961,"SHAPE_Area":8890226600.3917904}},{"type":"Feature","id":8,"geometry":{"type":"Polygon","coordinates":[[[847251.62179999985,722423.04120000079],[847251.62179999985,687828.17200000025],[978935.14800000004,687828.17200000025],[978935.14800000004,722423.04120000079],[847251.62179999985,722423.04120000079]]]},"properties":{"OBJECTID":8,"FeatureID":3316,"ZOrder":null,"AnnotationClassID":0,"SymbolID":0,"Status":0,"TextString":"West Coast","FontName":"BC Sans","FontStyle":"Regular","FontSize":9,"Underline":0,"VerticalAlignment":2,"HorizontalAlignment":1,"XOffset":0,"YOffset":0,"Angle":0,"FontLeading":0,"WordSpacing":100,"CharacterWidth":100,"CharacterSpacing":0,"FlipAngle":90,"Override":0,"SHAPE_Length":332556.79080000147,"SHAPE_Area":4555574364.6838512}}]}